autocast/__about__.py
autocast/__init__.py
autocast/_typing.py
autocast-0.0.1b1.dist-info/METADATA
autocast-0.0.1b1.dist-info/WHEEL
autocast-0.0.1b1.dist-info/licenses/LICENSE.txt
autocast-0.0.1b1.dist-info/RECORD
