Metadata-Version: 2.1
Name: autocast
Version: 0.0.1b1
Summary: Optional type coercion of function arguments.
Project-URL: Documentation, https://github.com/gchaperon/autocast#readme
Project-URL: Issues, https://github.com/gchaperon/autocast/issues
Project-URL: Source, https://github.com/gchaperon/autocast
Author-email: Gabriel Chaperon <gabrielchaperonb@gmail.com>
License-Expression: MIT
License-File: LICENSE.txt
Classifier: Development Status :: 4 - Beta
Classifier: Programming Language :: Python
Classifier: Programming Language :: Python :: 3.7
Classifier: Programming Language :: Python :: 3.8
Classifier: Programming Language :: Python :: 3.9
Classifier: Programming Language :: Python :: 3.10
Classifier: Programming Language :: Python :: 3.11
Classifier: Programming Language :: Python :: Implementation :: CPython
Classifier: Programming Language :: Python :: Implementation :: PyPy
Requires-Python: >=3.7
Requires-Dist: typing-extensions; python_version < '3.10'
